pikahandler/PikeHandler.py
pikahandler/__init__.py
pikahandler-0.0a1.dist-info/LICENSE
pikahandler-0.0a1.dist-info/METADATA
pikahandler-0.0a1.dist-info/WHEEL
pikahandler-0.0a1.dist-info/top_level.txt
pikahandler-0.0a1.dist-info/RECORD
