Metadata-Version: 2.1
Name: pikahandler
Version: 0.0a1
Summary: lalala
Home-page: https://github.com/whiteapfel/pikahandler
Author: WhiteApfel
Author-email: white@pfel.ru
License: Mozilla Public License 2.0
Project-URL: Документальное чтиво, https://pikahandler.readthedocs.io/ru/latest/
Project-URL: Донатик, https://rocketbank.ru/whiteapfel
Project-URL: Исходнички, https://github.com/WhiteApfel/pikahandler
Project-URL: Тележка для вопросов, https://t.me/apfel
Keywords: pika rabbitmq queue handler
Platform: UNKNOWN
Requires-Dist: pika
